androidstorage4kivy/__init__.py
androidstorage4kivy/chooser.py
androidstorage4kivy/sharedstorage.py
androidstorage4kivy/sharesheet.py
androidstorage4kivy-0.1.0.dist-info/LICENSE
androidstorage4kivy-0.1.0.dist-info/METADATA
androidstorage4kivy-0.1.0.dist-info/WHEEL
androidstorage4kivy-0.1.0.dist-info/top_level.txt
androidstorage4kivy-0.1.0.dist-info/RECORD
