Metadata-Version: 2.1
Name: androidstorage4kivy
Version: 0.1.0
Summary: A simple Android storage api
Home-page: https://github.com/Android-for-Python/androidstorage4kivy
Author: Robert Flatt
Classifier: Intended Audience :: Developers
Classifier: Topic :: Software Development :: Build Tools
Classifier: Programming Language :: Python :: 3
Classifier: License :: OSI Approved :: MIT License
Classifier: Operating System :: OS Independent
Requires-Python: >=3.6
License-File: LICENSE
